<?xml version="1.0" encoding="UTF-8"?>
<tour appversion="6.1.15" apprev="18116" start="node1">
  <panorama id="node1">
    <input levelbias="0.400" height="3521" leveltileurl="tiles/node1/cf_%c/l_%l/c_%x/tile_%y.jpg" width="3521" levelingpitch="0" leveltilesize="510" levelbiashidpi="1.000" overlap="1" levelingroll="0">
      <level height="3521" width="3521" predecode="0" preload="0"/>
      <level height="1760" width="1760" predecode="0" preload="0"/>
      <level height="880" width="880" predecode="0" preload="0"/>
      <level height="440" width="440" predecode="1" preload="1"/>
      <preview color="0x808080" strip="1"/>
    </input>
    <view pannorth="-180.812" fovmode="0">
      <start pan="1.18829" fov="70" projection="4" tilt="-7.98578"/>
      <flyin pan="0" fov="170" projection="9" tilt="-90"/>
      <min pan="0" fovpixel="2" tilt="-90"/>
      <max pan="360" fovstereographic="270" scaletofit="1" fov="120" tilt="90" fovfisheye="360"/>
    </view>
    <userdata author="" customnodeid="" description="" datetime="2/18/2020 7:03 AM" title="" longitude="-111.90722644" copyright="" comment="" tags="Node 2" info="" source="" latitude="40.41590988" heading="-180.812" nodeid="node1"/>
    <hotspots height="20" width="180" wordwrap="1">
      <label background="1" bordercolor="0x000000" height="20" backgroundcolor="0xffffff" backgroundalpha="1" enabled="1" width="180" border="1" textalpha="1" wordwrap="1" textcolor="0x000000" borderradius="1" borderalpha="1"/>
      <polystyle mode="0" bordercolor="0x0000ff" backgroundcolor="0x0000ff" handcursor="1" backgroundalpha="0.25098" borderalpha="1"/>
      <hotspot pan="-0.15" target="-7.6/-1.4/89.3" description="Move here" skinid="ht_node" title="" url="{node2}" id="Point01" distance="5.71726" tilt="14.56"/>
      <hotspot pan="313.18" target="-12.7/-1.3/70.0" description="Move here" skinid="ht_node" title="" url="{node3}" id="Point02" distance="5.45968" tilt="-6.94"/>
      <hotspot pan="-347.05" target="" description="" skinid="ht_image" title="Lost in the Bayou" url="images/Lost in the Bayou.png" id="Point03" tilt="30.5"/>
    </hotspots>
    <media/>
    <transition zoomin="0" zoomfov="20" zoomout="0" type="crossdissolve" zoomoutpause="1" zoomafteroutfov="20" enabled="1" blendtime="1" zoomspeed="2" blendcolor="0x000000" zoomafterinfov="90" softedge="0"/>
    <autorotate nodefilter="" startloaded="0" useanimation="0" nodedelay="0.00" noderandom="1" enabled="1" speed="0.050" delay="5.00" returntohorizon="0.000"/>
    <flyintransition enabled="1" speed="2.00"/>
    <animation useinautorotation="0" syncanimationwithvideo="0" animsequence="Animation01"/>
    <control invertwheel="0" sensitivity="8" contextfullscreen="1" invertcontrol="1" contextprojections="0" simulatemass="1" lockedmouse="0" lockedkeyboardzoom="0" dblclickfullscreen="0" lockedkeyboard="0" speedwheel="1" contextvr="1" rubberband="0" lockedwheel="0"/>
  </panorama>
  <panorama id="node2">
    <input levelbias="0.400" height="3480" leveltileurl="tiles/node2/cf_%c/l_%l/c_%x/tile_%y.jpg" width="3480" levelingpitch="0" leveltilesize="510" levelbiashidpi="1.000" overlap="1" levelingroll="0">
      <level height="3480" width="3480" predecode="0" preload="0"/>
      <level height="1740" width="1740" predecode="0" preload="0"/>
      <level height="870" width="870" predecode="0" preload="0"/>
      <level height="435" width="435" predecode="1" preload="1"/>
      <preview color="0x808080" strip="1"/>
    </input>
    <view pannorth="-156.714" fovmode="0">
      <start pan="0" fov="70" projection="4" tilt="0"/>
      <flyin pan="0" fov="170" projection="9" tilt="-90"/>
      <min pan="0" fovpixel="2" tilt="-90"/>
      <max pan="360" fovstereographic="270" scaletofit="1" fov="120" tilt="90" fovfisheye="360"/>
    </view>
    <userdata author="" customnodeid="" description="" datetime="2/18/2020 7:18 AM" title="" longitude="-111.90721839" copyright="" comment="" tags="Node 3" info="" source="" latitude="40.41585883" heading="-156.714" nodeid="node2"/>
    <hotspots height="20" width="180" wordwrap="1">
      <label background="1" bordercolor="0x000000" height="20" backgroundcolor="0xffffff" backgroundalpha="1" enabled="1" width="180" border="1" textalpha="1" wordwrap="1" textcolor="0x000000" borderradius="1" borderalpha="1"/>
      <polystyle mode="0" bordercolor="0x0000ff" backgroundcolor="0x0000ff" handcursor="1" backgroundalpha="0.25098" borderalpha="1"/>
      <hotspot pan="542.66" target="-12.8/-10.6/70.0" description="Move here" skinid="ht_node" title="" url="{node1}" id="Point01" distance="5.71726" tilt="-39.36"/>
      <hotspot pan="-22.57" target="138.2/-2.5/37.2" description="" skinid="ht_node" title="" url="{node4}" id="Point02" distance="5.148" tilt="-24.14"/>
      <hotspot pan="-206.74" target="" description="" skinid="ht_image" title="Lost in the Bayou" url="images/Lost in the Bayou.png" id="Point03" tilt="-14.24"/>
      <hotspot pan="-24.7" target="" description="" skinid="ht_image" title="Snow City" url="images/Snow CIty.png" id="Point04" tilt="-15.62"/>
      <hotspot pan="-31.66" target="" description="" skinid="ht_image" title="Festival of Lights" url="images/Festival of Lights.png" id="Point05" tilt="-14.97"/>
    </hotspots>
    <media/>
    <transition zoomin="0" zoomfov="20" zoomout="0" type="crossdissolve" zoomoutpause="1" zoomafteroutfov="20" enabled="1" blendtime="1" zoomspeed="2" blendcolor="0x000000" zoomafterinfov="90" softedge="0"/>
    <autorotate nodefilter="" startloaded="0" useanimation="0" nodedelay="0.00" noderandom="1" enabled="1" speed="0.050" delay="5.00" returntohorizon="0.000"/>
    <flyintransition enabled="1" speed="2.00"/>
    <animation useinautorotation="0" syncanimationwithvideo="0" animsequence="Animation01"/>
    <control invertwheel="0" sensitivity="8" contextfullscreen="1" invertcontrol="1" contextprojections="0" simulatemass="1" lockedmouse="0" lockedkeyboardzoom="0" dblclickfullscreen="0" lockedkeyboard="0" speedwheel="1" contextvr="1" rubberband="0" lockedwheel="0"/>
  </panorama>
  <panorama id="node3">
    <input levelbias="0.400" height="3482" leveltileurl="tiles/node3/cf_%c/l_%l/c_%x/tile_%y.jpg" width="3482" levelingpitch="0" leveltilesize="510" levelbiashidpi="1.000" overlap="1" levelingroll="0">
      <level height="3482" width="3482" predecode="0" preload="0"/>
      <level height="1741" width="1741" predecode="0" preload="0"/>
      <level height="870" width="870" predecode="0" preload="0"/>
      <level height="435" width="435" predecode="1" preload="1"/>
      <preview color="0x808080" strip="1"/>
    </input>
    <view pannorth="-187.008" fovmode="0">
      <start pan="0" fov="70" projection="4" tilt="0"/>
      <flyin pan="0" fov="170" projection="9" tilt="-90"/>
      <min pan="0" fovpixel="2" tilt="-90"/>
      <max pan="360" fovstereographic="270" scaletofit="1" fov="120" tilt="90" fovfisheye="360"/>
    </view>
    <userdata author="" customnodeid="" description="" datetime="2/18/2020 7:21 AM" title="" longitude="-111.90727204" copyright="" comment="" tags="Node 4" info="" source="" latitude="40.41587516" heading="-187.008" nodeid="node3"/>
    <hotspots height="20" width="180" wordwrap="1">
      <label background="1" bordercolor="0x000000" height="20" backgroundcolor="0xffffff" backgroundalpha="1" enabled="1" width="180" border="1" textalpha="1" wordwrap="1" textcolor="0x000000" borderradius="1" borderalpha="1"/>
      <polystyle mode="0" bordercolor="0x0000ff" backgroundcolor="0x0000ff" handcursor="1" backgroundalpha="0.25098" borderalpha="1"/>
      <hotspot pan="-7.05" target="21.5/-1.5/74.7" description="Move here" skinid="ht_node" title="" url="{node4}" id="Point02" distance="5.78782" tilt="-3.42"/>
      <hotspot pan="-219.97" target="-13.3/0.6/70.0" description="Move here" skinid="ht_node" title="" url="{node1}" id="Point03" distance="5.45968" tilt="-1.59"/>
      <hotspot pan="-171.29" target="" description="Ocean" skinid="ht_image" title="" url="images/Ocean.png" id="Point01" tilt="3.06"/>
      <hotspot pan="-352.36" target="" description="" skinid="ht_image" title="Snow City" url="images/Snow CIty.png" id="Point04" tilt="1.62"/>
      <hotspot pan="-1.07" target="" description="" skinid="ht_image" title="Festival of Lights" url="images/Festival of Lights.png" id="Point05" tilt="1.64"/>
    </hotspots>
    <media>
      <sound pan="-29.010" mode="2" tiltsize="10.000" loop="1" ambientlevel="0.000" level="0.150" id="Element01" field="90.000" pansize="10.000" startmutedmobile="0" tilt="-9.700" nodechangekeep="0">
        <source url="media/sound_fountain.mp3"/>
      </sound>
    </media>
    <transition zoomin="0" zoomfov="20" zoomout="0" type="crossdissolve" zoomoutpause="1" zoomafteroutfov="20" enabled="1" blendtime="1" zoomspeed="2" blendcolor="0x000000" zoomafterinfov="90" softedge="0"/>
    <autorotate nodefilter="" startloaded="0" useanimation="0" nodedelay="0.00" noderandom="1" enabled="1" speed="0.050" delay="5.00" returntohorizon="0.000"/>
    <flyintransition enabled="1" speed="2.00"/>
    <animation useinautorotation="0" syncanimationwithvideo="0" animsequence="Animation01"/>
    <control invertwheel="0" sensitivity="8" contextfullscreen="1" invertcontrol="1" contextprojections="0" simulatemass="1" lockedmouse="0" lockedkeyboardzoom="0" dblclickfullscreen="0" lockedkeyboard="0" speedwheel="1" contextvr="1" rubberband="0" lockedwheel="0"/>
  </panorama>
  <panorama id="node4">
    <input levelbias="0.400" height="3482" leveltileurl="tiles/node4/cf_%c/l_%l/c_%x/tile_%y.jpg" width="3482" levelingpitch="0" leveltilesize="510" levelbiashidpi="1.000" overlap="1" levelingroll="0">
      <level height="3482" width="3482" predecode="0" preload="0"/>
      <level height="1741" width="1741" predecode="0" preload="0"/>
      <level height="870" width="870" predecode="0" preload="0"/>
      <level height="435" width="435" predecode="1" preload="1"/>
      <preview color="0x808080" strip="1"/>
    </input>
    <view pannorth="-168.428" fovmode="0">
      <start pan="0" fov="70" projection="4" tilt="0"/>
      <flyin pan="0" fov="170" projection="9" tilt="-90"/>
      <min pan="0" fovpixel="2" tilt="-90"/>
      <max pan="360" fovstereographic="270" scaletofit="1" fov="120" tilt="90" fovfisheye="360"/>
    </view>
    <userdata author="" customnodeid="" description="" datetime="2/18/2020 7:29 AM" title="" longitude="-111.90725863" copyright="" comment="" tags="Node 5" info="" source="" latitude="40.41582412" heading="-168.428" nodeid="node4"/>
    <hotspots height="20" width="180" wordwrap="1">
      <label background="1" bordercolor="0x000000" height="20" backgroundcolor="0xffffff" backgroundalpha="1" enabled="1" width="180" border="1" textalpha="1" wordwrap="1" textcolor="0x000000" borderradius="1" borderalpha="1"/>
      <polystyle mode="0" bordercolor="0x0000ff" backgroundcolor="0x0000ff" handcursor="1" backgroundalpha="0.25098" borderalpha="1"/>
      <hotspot pan="-184.36" target="176.0/-0.8/70.0" description="" skinid="ht_node" title="" url="{node3}" id="Point03" distance="5.78782" tilt="-0.27"/>
      <hotspot pan="-227.86" target="154.4/-22.7/70.0" description="Move here" skinid="ht_node" title="" url="{node2}" id="Point01" distance="5.148" tilt="12.99"/>
      <hotspot pan="-333.82" target="" description="" skinid="ht_image" title="Festival of Lights" url="images/Festival of Lights.png" id="Point02" tilt="5.96"/>
      <hotspot pan="-313.45" target="" description="" skinid="ht_image" title="Snow City" url="images/Snow CIty.png" id="Point04" tilt="5.35"/>
      <hotspot pan="-208.67" target="" description="" skinid="ht_image" title="Tea Time in All the Seasons" url="images/Tea Time in All the Seasons.png" id="Point05" tilt="-1.58"/>
    </hotspots>
    <media>
      <video pan="-230.910" tiltsize="10.000" height="270" rotz="-6.000" fov="15.970" field="90.000" width="480" roty="-58.000" startmutedmobile="0" mode="1" pansize="10.000" tilt="-2.850" loop="1" ambientlevel="0.100" handcursor="0" level="1.000" nodechangekeep="0" rotx="-7.000" clickmode="0" stretch="1.000" id="Element01">
        <source url="media/Puppet - 1405.mp4"/>
      </video>
      <sound pan="-147.340" mode="2" tiltsize="10.000" loop="1" ambientlevel="0.000" level="0.200" id="Element02" field="90.000" pansize="10.000" startmutedmobile="0" tilt="-16.280" nodechangekeep="0">
        <source url="media/sound_fountain.mp3"/>
      </sound>
    </media>
    <transition zoomin="0" zoomfov="20" zoomout="0" type="crossdissolve" zoomoutpause="1" zoomafteroutfov="20" enabled="1" blendtime="1" zoomspeed="2" blendcolor="0x000000" zoomafterinfov="90" softedge="0"/>
    <autorotate nodefilter="" startloaded="0" useanimation="0" nodedelay="0.00" noderandom="1" enabled="1" speed="0.050" delay="5.00" returntohorizon="0.000"/>
    <flyintransition enabled="1" speed="2.00"/>
    <animation useinautorotation="0" syncanimationwithvideo="0" animsequence="Animation01"/>
    <control invertwheel="0" sensitivity="8" contextfullscreen="1" invertcontrol="1" contextprojections="0" simulatemass="1" lockedmouse="0" lockedkeyboardzoom="0" dblclickfullscreen="0" lockedkeyboard="0" speedwheel="1" contextvr="1" rubberband="0" lockedwheel="0"/>
  </panorama>
  <masternode>
    <userdata author="" customnodeid="" description="" datetime="" title="" longitude="" copyright="" comment="" tags="" info="" source="" latitude="" heading="0" nodeid="master"/>
  </masternode>
  <map mapurltemplate="http://{s}.tile.openstreetmap.org/{z}/{x}/{y}.png" type="web" mapprovider="openstreetmap" title="" id="Map01" mapstyle="streets" mapmaxzoom="18"/>
</tour>
